imbDRL/__init__.py
imbDRL/data.py
imbDRL/metrics.py
imbDRL/utils.py
imbDRL/agents/__init__.py
imbDRL/agents/ddqn.py
imbDRL/environments/__init__.py
imbDRL/environments/classifierenv.py
imbDRL/examples/__init__.py
imbDRL/examples/ddqn/__init__.py
imbDRL/examples/ddqn/analyse_model.py
imbDRL/examples/ddqn/train_aki.py
imbDRL/examples/ddqn/train_credit.py
imbDRL/examples/ddqn/train_famnist.py
imbDRL/examples/ddqn/train_imdb.py
imbDRL/examples/ddqn/train_mnist.py
imbDRL/examples/ddqn/train_titanic.py
imbDRL-2021.1.26.1.dist-info/LICENSE
imbDRL-2021.1.26.1.dist-info/METADATA
imbDRL-2021.1.26.1.dist-info/WHEEL
imbDRL-2021.1.26.1.dist-info/top_level.txt
imbDRL-2021.1.26.1.dist-info/RECORD
