Metadata-Version: 2.1
Name: imbDRL
Version: 2021.1.26.1
Summary: Imbalanced Classification with Deep Reinforcement Learning.
Home-page: https://github.com/Denbergvanthijs/imbDRL
Author: Thijs van den Berg
Author-email: denbergvanthijs@gmail.com
License: UNKNOWN
Keywords: imbalanced classification,deep reinforcement learning,deep q-network,reward-function,classification,medical
Platform: UNKNOWN
Classifier: Programming Language :: Python :: 3
Classifier: License :: OSI Approved :: Apache Software License
Classifier: Operating System :: OS Independent
Classifier: Environment :: GPU :: NVIDIA CUDA
Classifier: Topic :: Scientific/Engineering :: Artificial Intelligence
Requires-Python: >=3.7
Requires-Dist: tensorflow (>=2.3)
Requires-Dist: tf-agents (>=0.6.0)
Requires-Dist: numpy (!=1.19.4)
Requires-Dist: gym
Requires-Dist: matplotlib
Requires-Dist: pandas
Requires-Dist: seaborn
Requires-Dist: sklearn
Requires-Dist: tqdm
